MANIFEST.in
README.md
setup.py
django_system_monitor.egg-info/PKG-INFO
django_system_monitor.egg-info/SOURCES.txt
django_system_monitor.egg-info/dependency_links.txt
django_system_monitor.egg-info/requires.txt
django_system_monitor.egg-info/top_level.txt
sysmon/__init__.py
sysmon/admin.py
sysmon/templates/sysmon/index.html
sysmon/templatetags/__init__.py
sysmon/templatetags/sysmon_tags.py
sysmon/tests/__init__.py
sysmon/tests/test_bytes2human.py
sysmon/tests/test_sysmon_tags.py