Metadata-Version: 1.1
Name: django-system-monitor
Version: 0.5
Summary: View simple system statistics in django admin panel
Home-page: https://github.com/hakanzy/django-system-monitor
Author: Hakan OZAY
Author-email: hakanzy@gmail.com
License: UNKNOWN
Platform: UNKNOWN
Classifier: Development Status :: 4 - Beta
Classifier: Environment :: Web Environment
Classifier: Intended Audience :: Developers
Classifier: License :: OSI Approved :: BSD License
Classifier: Operating System :: OS Independent
Classifier: Programming Language :: Python
Classifier: Framework :: Django
